noaa/__init__.py
noaa/get_historical_weather.py
noaa_weather-0.1.data/scripts/get_historical_weather.py
noaa_weather-0.1.dist-info/METADATA
noaa_weather-0.1.dist-info/WHEEL
noaa_weather-0.1.dist-info/top_level.txt
noaa_weather-0.1.dist-info/RECORD
