Metadata-Version: 2.1
Name: noaa-weather
Version: 0.1
Summary: A bulk historical weather data from National Oceanic and Atmospheric Administration.
Home-page: https://github.com/celikfatih
Author: Fatih Celik
Author-email: fatih.celik@b2metric.com
License: UNKNOWN
Platform: UNKNOWN
Classifier: Programming Language :: Python :: 3
Classifier: License :: OSI Approved :: MIT License
Classifier: Operating System :: OS Independent
